terrarium_assembler_win/__init__.py
terrarium_assembler_win/cli.py
terrarium_assembler_win/nuitkaflags.py
terrarium_assembler_win/ta.py
terrarium_assembler_win/utils.py
terrarium_assembler_win/wheel_utils.py
terrarium_assembler_win/windows-builder.py
terrarium_assembler_win-0.0.3.dist-info/LICENSE
terrarium_assembler_win-0.0.3.dist-info/METADATA
terrarium_assembler_win-0.0.3.dist-info/WHEEL
terrarium_assembler_win-0.0.3.dist-info/entry_points.txt
terrarium_assembler_win-0.0.3.dist-info/top_level.txt
terrarium_assembler_win-0.0.3.dist-info/RECORD
