Metadata-Version: 2.1
Name: terrarium-assembler-win
Version: 0.0.3
Summary: Generate Portable Windows Applications
Home-page: https://github.com/belonesox/terrarium_assembler_win
Author: Stas Fomin
Author-email: stas-fomin@yandex.ru
License: MIT license
Keywords: terrarium_assembler
Platform: UNKNOWN
Classifier: Development Status :: 2 - Pre-Alpha
Classifier: Intended Audience :: Developers
Classifier: License :: OSI Approved :: MIT License
Classifier: Natural Language :: English
Classifier: Programming Language :: Python :: 3
Classifier: Programming Language :: Python :: 3.7
Classifier: Programming Language :: Python :: 3.8
Requires-Python: >=3.7
Requires-Dist: easydict
Requires-Dist: pytictoc
Requires-Dist: file-magic
Requires-Dist: jinja2
Requires-Dist: packaging
Requires-Dist: wheel-filename
